[
  {
    "comment": "Country code overrides for ukrainian users.",
    "defaults": [
      "ru"
    ],
    "locales": [
      "ua",
      "uk"
    ],
    "target": 196,
    "cities": [
      "алупка",
      "алушта",
      "армянск",
      "бахчисарай",
      "белогорск",
      "джанкой",
      "евпатория",
      "керчь",
      "красноперекопск",
      "саки",
      "симферополь",
      "старый крым",
      "судак",
      "феодосия",
      "щёлкино",
      "ялта",
      "севастополь"
    ]
  }
]